dp_sequence_editor/__init__.py
dp_sequence_editor/frontend/build/asset-manifest.json
dp_sequence_editor/frontend/build/bootstrap.min.css
dp_sequence_editor/frontend/build/index.html
dp_sequence_editor/frontend/build/static/css/main.1a0bab6b.css
dp_sequence_editor/frontend/build/static/css/main.1a0bab6b.css.map
dp_sequence_editor/frontend/build/static/js/main.6c92e5b4.js
dp_sequence_editor/frontend/build/static/js/main.6c92e5b4.js.LICENSE.txt
dp_sequence_editor/frontend/build/static/js/main.6c92e5b4.js.map
dp_sequence_editor-0.0.1.dist-info/LICENSE
dp_sequence_editor-0.0.1.dist-info/METADATA
dp_sequence_editor-0.0.1.dist-info/WHEEL
dp_sequence_editor-0.0.1.dist-info/top_level.txt
dp_sequence_editor-0.0.1.dist-info/RECORD
